<?xml version="1.0" encoding="utf-8"?><AttributeDefinition xmlns:xsi="http://www.w3.org/2001/XMLSchema-instance" xmlns:xsd="http://www.w3.org/2001/XMLSchema" xsi:noNamespaceSchemaLocation="DaVinciEx_GenericAttributes_1_0.xsd" dvSchemaVersion="1.0"><AttributeDefinitionTable Version="1.0" ID="{932D3FD0-2F6C-49BF-80CB-D1C3756D3868}"><Attribute Name="IMPORT_MODE_PRESET_COMPONENT" ObjectType="ComponentType"><ENUM Default="Keep"><EnumValue Value="Keep" /><EnumValue Value="Overwrite" /></ENUM></Attribute><Attribute Name="IMPORT_MODE_PRESET_PORT" ObjectType="PortPrototype"><ENUM Default="Keep"><EnumValue Value="Keep" /><EnumValue Value="Overwrite" /></ENUM></Attribute></AttributeDefinitionTable><ObjectAttributeReference ObjectType="Port Prototype"><ARObjectReference Type="R-PORT-PROTOTYPE" Reference="/ComponentTypes/AAACalRegn02Rt01GroupB_Dummy/EotProtnDampgVehSpdTbl" /><AttributeDefinitionTableRef Version="1.0" ID="{932D3FD0-2F6C-49BF-80CB-D1C3756D3868}" /><AttributeValue Name="IMPORT_MODE_PRESET_PORT" Value="Overwrite" /></ObjectAttributeReference><ObjectAttributeReference ObjectType="Port Prototype"><ARObjectReference Type="R-PORT-PROTOTYPE" Reference="/ComponentTypes/AAACalRegn02Rt01GroupB_Dummy/EotProtnDeltaTqThd" /><AttributeDefinitionTableRef Version="1.0" ID="{932D3FD0-2F6C-49BF-80CB-D1C3756D3868}" /><AttributeValue Name="IMPORT_MODE_PRESET_PORT" Value="Overwrite" /></ObjectAttributeReference><ObjectAttributeReference ObjectType="Port Prototype"><ARObjectReference Type="R-PORT-PROTOTYPE" Reference="/ComponentTypes/AAACalRegn02Rt01GroupB_Dummy/EotProtnEntrGainVehSpdTbl" /><AttributeDefinitionTableRef Version="1.0" ID="{932D3FD0-2F6C-49BF-80CB-D1C3756D3868}" /><AttributeValue Name="IMPORT_MODE_PRESET_PORT" Value="Overwrite" /></ObjectAttributeReference><ObjectAttributeReference ObjectType="Port Prototype"><ARObjectReference Type="R-PORT-PROTOTYPE" Reference="/ComponentTypes/AAACalRegn02Rt01GroupB_Dummy/EotProtnEntrGainY" /><AttributeDefinitionTableRef Version="1.0" ID="{932D3FD0-2F6C-49BF-80CB-D1C3756D3868}" /><AttributeValue Name="IMPORT_MODE_PRESET_PORT" Value="Overwrite" /></ObjectAttributeReference><ObjectAttributeReference ObjectType="Port Prototype"><ARObjectReference Type="R-PORT-PROTOTYPE" Reference="/ComponentTypes/AAACalRegn02Rt01GroupB_Dummy/EotProtnLoAuthyEntrGainY" /><AttributeDefinitionTableRef Version="1.0" ID="{932D3FD0-2F6C-49BF-80CB-D1C3756D3868}" /><AttributeValue Name="IMPORT_MODE_PRESET_PORT" Value="Overwrite" /></ObjectAttributeReference><ObjectAttributeReference ObjectType="Port Prototype"><ARObjectReference Type="R-PORT-PROTOTYPE" Reference="/ComponentTypes/AAACalRegn02Rt01GroupB_Dummy/EotProtnMotSpdIncptY" /><AttributeDefinitionTableRef Version="1.0" ID="{932D3FD0-2F6C-49BF-80CB-D1C3756D3868}" /><AttributeValue Name="IMPORT_MODE_PRESET_PORT" Value="Overwrite" /></ObjectAttributeReference><ObjectAttributeReference ObjectType="Port Prototype"><ARObjectReference Type="R-PORT-PROTOTYPE" Reference="/ComponentTypes/AAACalRegn02Rt01GroupB_Dummy/EotProtnNormDampgY" /><AttributeDefinitionTableRef Version="1.0" ID="{932D3FD0-2F6C-49BF-80CB-D1C3756D3868}" /><AttributeValue Name="IMPORT_MODE_PRESET_PORT" Value="Overwrite" /></ObjectAttributeReference><ObjectAttributeReference ObjectType="Port Prototype"><ARObjectReference Type="R-PORT-PROTOTYPE" Reference="/ComponentTypes/AAACalRegn02Rt01GroupB_Dummy/EotProtnSoftEndStopAuthyThd" /><AttributeDefinitionTableRef Version="1.0" ID="{932D3FD0-2F6C-49BF-80CB-D1C3756D3868}" /><AttributeValue Name="IMPORT_MODE_PRESET_PORT" Value="Overwrite" /></ObjectAttributeReference><ObjectAttributeReference ObjectType="Port Prototype"><ARObjectReference Type="R-PORT-PROTOTYPE" Reference="/ComponentTypes/AAACalRegn02Rt01GroupB_Dummy/RtnHwAgOffsCalcdX" /><AttributeDefinitionTableRef Version="1.0" ID="{932D3FD0-2F6C-49BF-80CB-D1C3756D3868}" /><AttributeValue Name="IMPORT_MODE_PRESET_PORT" Value="Overwrite" /></ObjectAttributeReference><ObjectAttributeReference ObjectType="Port Prototype"><ARObjectReference Type="R-PORT-PROTOTYPE" Reference="/ComponentTypes/AAACalRegn02Rt01GroupB_Dummy/RtnHwAgOffsCalcdY" /><AttributeDefinitionTableRef Version="1.0" ID="{932D3FD0-2F6C-49BF-80CB-D1C3756D3868}" /><AttributeValue Name="IMPORT_MODE_PRESET_PORT" Value="Overwrite" /></ObjectAttributeReference><ObjectAttributeReference ObjectType="Port Prototype"><ARObjectReference Type="R-PORT-PROTOTYPE" Reference="/ComponentTypes/AAACalRegn02Rt01GroupB_Dummy/RtnScaTqX" /><AttributeDefinitionTableRef Version="1.0" ID="{932D3FD0-2F6C-49BF-80CB-D1C3756D3868}" /><AttributeValue Name="IMPORT_MODE_PRESET_PORT" Value="Overwrite" /></ObjectAttributeReference><ObjectAttributeReference ObjectType="Port Prototype"><ARObjectReference Type="R-PORT-PROTOTYPE" Reference="/ComponentTypes/AAACalRegn02Rt01GroupB_Dummy/RtnScaTqY" /><AttributeDefinitionTableRef Version="1.0" ID="{932D3FD0-2F6C-49BF-80CB-D1C3756D3868}" /><AttributeValue Name="IMPORT_MODE_PRESET_PORT" Value="Overwrite" /></ObjectAttributeReference><ObjectAttributeReference ObjectType="Port Prototype"><ARObjectReference Type="R-PORT-PROTOTYPE" Reference="/ComponentTypes/AAACalRegn02Rt01GroupB_Dummy/RtnScaVelX" /><AttributeDefinitionTableRef Version="1.0" ID="{932D3FD0-2F6C-49BF-80CB-D1C3756D3868}" /><AttributeValue Name="IMPORT_MODE_PRESET_PORT" Value="Overwrite" /></ObjectAttributeReference><ObjectAttributeReference ObjectType="Port Prototype"><ARObjectReference Type="R-PORT-PROTOTYPE" Reference="/ComponentTypes/AAACalRegn02Rt01GroupB_Dummy/RtnScaVelY" /><AttributeDefinitionTableRef Version="1.0" ID="{932D3FD0-2F6C-49BF-80CB-D1C3756D3868}" /><AttributeValue Name="IMPORT_MODE_PRESET_PORT" Value="Overwrite" /></ObjectAttributeReference><ObjectAttributeReference ObjectType="Port Prototype"><ARObjectReference Type="R-PORT-PROTOTYPE" Reference="/ComponentTypes/AAACalRegn02Rt01GroupB_Dummy/RtnVehSpdSeln" /><AttributeDefinitionTableRef Version="1.0" ID="{932D3FD0-2F6C-49BF-80CB-D1C3756D3868}" /><AttributeValue Name="IMPORT_MODE_PRESET_PORT" Value="Overwrite" /></ObjectAttributeReference><ObjectAttributeReference ObjectType="Component Type"><ARObjectReference Type="APPLICATION-SW-COMPONENT-TYPE" Reference="/ComponentTypes/AAACalRegn02Rt01GroupB_Dummy" /><AttributeDefinitionTableRef Version="1.0" ID="{932D3FD0-2F6C-49BF-80CB-D1C3756D3868}" /><AttributeValue Name="IMPORT_MODE_PRESET_COMPONENT" Value="Overwrite" /></ObjectAttributeReference></AttributeDefinition>